haohaoxuexi/__init__.py
haohaoxuexi/demo1.py
haohaoxuexi/demo2.py
haohaoxuexi/c2/tank01.py
haohaoxuexi/tk/__init__.py
haohaoxuexi/tk/drawpad.py
haohaoxuexi/tk/notepad.py
haohaoxuexi/tk/test.py
haohaoxuexi/tk/tk.py
haohaoxuexi-1.0.2.dist-info/METADATA
haohaoxuexi-1.0.2.dist-info/WHEEL
haohaoxuexi-1.0.2.dist-info/top_level.txt
haohaoxuexi-1.0.2.dist-info/RECORD
