Metadata-Version: 2.1
Name: haohaoxuexi
Version: 1.0.2
Summary: v1.0.1 加入tk模块(tkinter组件编写实例)
Author: zqd
Author-email: 
License: UNKNOWN
Platform: UNKNOWN
